[
    {
        "name": "pp.01-05",

        "activeLeg": 
            {
                "vtSymbol": "pp1901",
                "ratio": 1,
                "multiplier": 1.0,
                "payup": 1
            },

        "passiveLegs": [
            {
                "vtSymbol": "pp1905",
                "ratio": -1,
                "multiplier": -1.0,
                "payup": 1
            }
        ]
    },
    
    {
        "name": "SF.01-05",

        "activeLeg": 
            {
                "vtSymbol": "SF901",
                "ratio": 1,
                "multiplier": 1.0,
                "payup": 1
            },

        "passiveLegs": [
            {
                "vtSymbol": "SF905",
                "ratio": -1,
                "multiplier": -1,
                "payup": 1
            }
        ]
    },
    
    {
        "name": "FG.01-05",

        "activeLeg": 
            {
                "vtSymbol": "FG901",
                "ratio": 1,
                "multiplier": 1.0,
                "payup": 1
            },

        "passiveLegs": [
            {
                "vtSymbol": "FG905",
                "ratio": -1,
                "multiplier": -1,
                "payup": 1
            }
        ]
    },
    
    {
        "name": "al.01-02",

        "activeLeg": 
            {
                "vtSymbol": "al1901",
                "ratio": 1,
                "multiplier": 1.0,
                "payup": 1
            },

        "passiveLegs": [
            {
                "vtSymbol": "al1902",
                "ratio": -1,
                "multiplier": -1.0,
                "payup": 1
            }
        ]
    },
    
    {
        "name": "ag.12-06",

        "activeLeg": 
            {
                "vtSymbol": "ag1912",
                "ratio": 1,
                "multiplier": 1.0,
                "payup": 1
            },

        "passiveLegs": [
            {
                "vtSymbol": "ag1906",
                "ratio": -1,
                "multiplier": -1,
                "payup": 1
            }
        ]
    },
    
    {
        "name": "MA.01-05",

        "activeLeg": 
            {
                "vtSymbol": "MA901",
                "ratio": 1,
                "multiplier": 1.0,
                "payup": 1
            },

        "passiveLegs": [
            {
                "vtSymbol": "MA905",
                "ratio": -1,
                "multiplier": -1,
                "payup": 1
            }
        ]
    }, 
    
    {
        "name": "jd.01-05",

        "activeLeg": 
            {
                "vtSymbol": "jd1901",
                "ratio": 1,
                "multiplier": 1.0,
                "payup": 1
            },

        "passiveLegs": [
            {
                "vtSymbol": "jd1905",
                "ratio": -1,
                "multiplier": -1.0,
                "payup": 1
            }
        ]
    },
    
    {
        "name": "bu.12-06",

        "activeLeg": 
            {
                "vtSymbol": "bu1912",
                "ratio": 1,
                "multiplier": 1.0,
                "payup": 1
            },

        "passiveLegs": [
            {
                "vtSymbol": "bu1906",
                "ratio": -1,
                "multiplier": -1,
                "payup": 1
            }
        ]
    },
    
    {
        "name": "hc.01-05",

        "activeLeg": 
            {
                "vtSymbol": "hc1901",
                "ratio": 1,
                "multiplier": 1.0,
                "payup": 1
            },

        "passiveLegs": [
            {
                "vtSymbol": "hc1905",
                "ratio": -1,
                "multiplier": -1,
                "payup": 1
            }
        ]
    },
    
    {
        "name": "rb.01-05",

        "activeLeg": 
            {
                "vtSymbol": "rb1901",
                "ratio": 1,
                "multiplier": 1.0,
                "payup": 1
            },

        "passiveLegs": [
            {
                "vtSymbol": "rb1905",
                "ratio": -1,
                "multiplier": -1,
                "payup": 1
            }
        ]
    }
    
]